prism/__init__.py
prism/layer.py
prism/model.py
prism/train.py
prism/utils.py
prism/version.py
prism_grn-1.2.0.dist-info/METADATA
prism_grn-1.2.0.dist-info/WHEEL
prism_grn-1.2.0.dist-info/top_level.txt
prism_grn-1.2.0.dist-info/RECORD
