Metadata-Version: 2.1
Name: prism_grn
Version: 1.2.0
Summary: A Probabilistic Model for Recovering GRNs based on Multi-Omics Data
Home-page: https://github.com/Ying-Lab/PRISM/
Author: Wenhao Zhang
Author-email: zscotty@stu.xmu.edu.cn
License: MIT
Classifier: License :: OSI Approved :: MIT License
Classifier: Programming Language :: Python :: 3
Classifier: Programming Language :: Python :: 3.8
Classifier: Programming Language :: Python :: 3.9
Classifier: Programming Language :: Python :: Implementation :: CPython
Classifier: Programming Language :: Python :: Implementation :: PyPy
Requires-Python: >=3.8.10
Requires-Dist: torch==1.11.0
Requires-Dist: pyro-ppl==1.7.0
Requires-Dist: networkx==3.1
Requires-Dist: numpy==1.24.4
Requires-Dist: scipy==1.10.1
Requires-Dist: pandas==2.0.3
Provides-Extra: dev
Requires-Dist: pytest; extra == "dev"
Requires-Dist: black; extra == "dev"
Requires-Dist: flake8; extra == "dev"
